odoo10_addon_product_assortment-10.0.1.0.0.99.dev5-py3.8-nspkg.pth
odoo/addons/product_assortment/README.rst
odoo/addons/product_assortment/__init__.py
odoo/addons/product_assortment/__manifest__.py
odoo/addons/product_assortment/i18n/product_assortment.pot
odoo/addons/product_assortment/models/__init__.py
odoo/addons/product_assortment/models/ir_filters.py
odoo/addons/product_assortment/readme/CONTRIBUTORS.rst
odoo/addons/product_assortment/readme/DESCRIPTION.rst
odoo/addons/product_assortment/readme/USAGE.rst
odoo/addons/product_assortment/static/description/icon.png
odoo/addons/product_assortment/static/description/index.html
odoo/addons/product_assortment/tests/__init__.py
odoo/addons/product_assortment/tests/test_product_assortment.py
odoo/addons/product_assortment/views/product_assortment.xml
odoo10_addon_product_assortment-10.0.1.0.0.99.dev5.dist-info/METADATA
odoo10_addon_product_assortment-10.0.1.0.0.99.dev5.dist-info/WHEEL
odoo10_addon_product_assortment-10.0.1.0.0.99.dev5.dist-info/namespace_packages.txt
odoo10_addon_product_assortment-10.0.1.0.0.99.dev5.dist-info/top_level.txt
odoo10_addon_product_assortment-10.0.1.0.0.99.dev5.dist-info/RECORD
